streebog_rs-0.2.0.dist-info/METADATA
streebog_rs-0.2.0.dist-info/WHEEL
streebog_rs/__init__.py
streebog_rs/streebog_rs.cpython-311-darwin.so
streebog_rs-0.2.0.dist-info/RECORD
