Metadata-Version: 2.4
Name: streebog_rs
Version: 0.2.0
Classifier: Programming Language :: Rust
Classifier: Programming Language :: Python :: Implementation :: CPython
Classifier: Programming Language :: Python :: Implementation :: PyPy
Requires-Dist: maturin>=1.9.1,<2.0.0
Summary: 
Author-email: Vadim Grigortsev <dev@shitposting.team>
Requires-Python: >=3.9
